LICENSE.txt
MANIFEST.in
README.md
setup.cfg
setup.py
afrigis/__init__.py
afrigis/authentication.py
afrigis/exceptions.py
afrigis/services.py
afrigis/url_creator.py
afrigis.egg-info/PKG-INFO
afrigis.egg-info/SOURCES.txt
afrigis.egg-info/dependency_links.txt
afrigis.egg-info/top_level.txt
afrigis/tests/__init__.py
afrigis/tests/mocks.py
afrigis/tests/test_authentication.py
afrigis/tests/test_geocode.py
afrigis/tests/test_url_creator.py