Metadata-Version: 2.1
Name: afrigis
Version: 0.1.0.dev1
Summary: Afrigis Python Library
Home-page: https://github.com/chris-cmsoft/python-afrigis
Author: Chris Vermeulen
Author-email: chris@cmsoft.co.za
License: UNKNOWN
Project-URL: Bug Reports, https://github.com/chris-cmsoft/python-afrigis/issues
Project-URL: Source, https://github.com/chris-cmsoft/python-afrigis/
Keywords: Python Afrigis Integration
Platform: UNKNOWN
Classifier: Development Status :: 1 - Planning
Classifier: Intended Audience :: Developers
Classifier: Topic :: Software Development :: Libraries
Classifier: Topic :: Software Development :: Libraries :: Python Modules
Classifier: License :: OSI Approved :: MIT License
Classifier: Programming Language :: Python
Classifier: Programming Language :: Python :: 2
Classifier: Programming Language :: Python :: 2.6
Classifier: Programming Language :: Python :: 2.7
Classifier: Programming Language :: Python :: 3
Classifier: Programming Language :: Python :: 3.4
Classifier: Programming Language :: Python :: 3.5
Classifier: Programming Language :: Python :: 3.6
Requires-Python: >=2.7, !=3.0.*, !=3.1.*, !=3.2.*, <4
